setup.py
feedbloom/__init__.py
feedbloom/feedbloom.py
feedbloom.egg-info/PKG-INFO
feedbloom.egg-info/SOURCES.txt
feedbloom.egg-info/dependency_links.txt
feedbloom.egg-info/entry_points.txt
feedbloom.egg-info/not-zip-safe
feedbloom.egg-info/requires.txt
feedbloom.egg-info/top_level.txt