Metadata-Version: 1.1
Name: feedbloom
Version: 0.1.3
Summary: Feed Reader inspired by news channels bottom stripes.
Home-page: http://github.com/eduardostalinho/feedbloom
Author: Eduardo Stalinho
Author-email: eduardooc.86@gmail.com
License: GPLv3
Platform: UNKNOWN
Classifier: Programming Language :: Python :: 3 :: Only
Classifier: Development Status :: 3 - Alpha
Classifier: Environment :: Console
Classifier: Intended Audience :: End Users/Desktop
Classifier: Topic :: Utilities
